fkbutils/__init__.py
fkbutils/dbwrapper/__init__.py
fkbutils/dbwrapper/mongo.py
fkbutils/dbwrapper/postgres.py
fkbutils/dbwrapper/redis.py
fkbutils/misc/__init__.py
fkbutils/misc/config_manager.py
fkbutils/ml/__init__.py
fkbutils/ml/preprocessing.py
tests/__init__.py
fkbutils-0.2.1.dist-info/LICENSE
fkbutils-0.2.1.dist-info/METADATA
fkbutils-0.2.1.dist-info/WHEEL
fkbutils-0.2.1.dist-info/top_level.txt
fkbutils-0.2.1.dist-info/RECORD
