Metadata-Version: 2.1
Name: fkbutils
Version: 0.2.1
Summary: Utility functions that I need often across multiple projects!
Home-page: UNKNOWN
Author: Felix Kleine Bösing
Author-email: felix.boesing@t-online.de
License: UNKNOWN
Platform: UNKNOWN
Requires-Dist: pandas (>=1.1.4)
Requires-Dist: numpy (>=1.18.5)
Requires-Dist: redis (>=3.5.3)
Requires-Dist: psycopg2 (>=2.8.6)
Requires-Dist: pymongo (>=3.11)
Requires-Dist: python-dotenv
